ejercicio3/counter.sv
module counter#(parameter N =16)(clk,rst, countout);
input clk;
input rst;
output [N-1:0] countout;

wire clk;
wire rst;

reg countout = 0;

always @(posedge clk or negedge rst)         
begin   
	if(rst ===0)
		countout <=0;
	else
		$display("Iniciando contador. Reloj: %d. Reset: %d",clk, rst);
		countout<= countout + 1;
		$display("Valor del contador: %d",countout);


end // Fin del bloque COUNTER
endmodule

ejercicio3/counter_tb.sv
//-- counter_tb.v
module counter_tb();
	 
//-- Registro para generar la señal de reloj
reg clk = 0;
reg rst = 1;
	 
//-- Datos de salida del contador
wire  data;

//-- Registro para comprobar si el contador cuenta correctamente
reg [5:0] counter_check = 0;
	 
//-- Instanciar el contador
counter #(5) C1(clk,rst, data);
	 
//-- Generador de reloj. Periodo 2 unidades
always #2 clk = ~clk;
	 
//-- Comprobacion del valor del contador
//-- En cada flanco de bajada se comprueba la salida del contador
//-- y se incrementa el valor esperado
	 
//-- Proceso al inicio
always @(negedge clk) begin 
	  $display("counter clk: %d. data: %d",counter_check, data); 
	  counter_check <= counter_check + 1;
	end
initial begin
	 
  //-- Fichero donde almacenar los resultados
  $dumpfile("counter_tb.vcd");
  $dumpvars(0, counter_tb);
	 
  //-- Comprobación del reset.
  # 0.5 if (data != 0)
			 $display("ERROR! Contador NO está a 0!");
		  else
			 $display("Contador inicializado. OK.");
  #40
  rst = 0;
  $display("Data",data);
  # 99 $display("FIN de la simulacion");
  # 100 $finish;
 end
 endmodule

ejercicio3/simulation/modelsim/counter_tb.vcd
$date
	Sat Aug 21 20:52:53 2021
$end
$version
	ModelSim Version 2020.1
$end
$timescale
	1ps
$end

$scope module counter_tb $end
$var reg 1 ! clk $end
$var reg 1 " rst $end
$var wire 1 # data $end
$var reg 6 $ counter_check [5:0] $end

$scope module C1 $end
$var parameter 32 % N $end
$var wire 1 & clk $end
$var wire 1 ' rst $end
$var reg 1 ( countout $end
$upscope $end
$upscope $end
$enddefinitions $end
#0
$dumpvars
0!
1"
b0 $
0(
b101 %
0#
0&
1'
$end
#2
1!
1&
1(
1#
#4
0!
0&
b1 $
#6
1!
1&
0(
0#
#8
0!
0&
b10 $
#10
1!
1&
1(
1#
#12
0!
0&
b11 $
#14
1!
1&
0(
0#
#16
0!
0&
b100 $
#18
1!
1&
1(
1#
#20
0!
0&
b101 $
#22
1!
1&
0(
0#
#24
0!
0&
b110 $
#26
1!
1&
1(
1#
#28
0!
0&
b111 $
#30
1!
1&
0(
0#
#32
0!
0&
b1000 $
#34
1!
1&
1(
1#
#36
0!
0&
b1001 $
#38
1!
1&
0(
0#
#40
0!
0&
b1010 $
#41
0"
0'
1(
1#
#42
1!
1&
0(
0#
#44
0!
0&
b1011 $
#46
1!
1&
1(
1#
#48
0!
0&
b1100 $
#50
1!
1&
0(
0#
#52
0!
0&
b1101 $
#54
1!
1&
1(
1#
#56
0!
0&
b1110 $
#58
1!
1&
0(
0#
#60
0!
0&
b1111 $
#62
1!
1&
1(
1#
#64
0!
0&
b10000 $
#66
1!
1&
0(
0#
#68
0!
0&
b10001 $
#70
1!
1&
1(
1#
#72
0!
0&
b10010 $
#74
1!
1&
0(
0#
#76
0!
0&
b10011 $
#78
1!
1&
1(
1#
#80
0!
0&
b10100 $
#82
1!
1&
0(
0#
#84
0!
0&
b10101 $
#86
1!
1&
1(
1#
#88
0!
0&
b10110 $
#90
1!
1&
0(
0#
#92
0!
0&
b10111 $
#94
1!
1&
1(
1#
#96
0!
0&
b11000 $
#98
1!
1&
0(
0#
#100
0!
0&
b11001 $
